pnwtools/CheckTags.py
pnwtools/GetStationInfo.py
pnwtools/MakeWavReviewFile.py
pnwtools/RenameFiles.py
pnwtools/__init__.py
pnwtools-2024.8.20.dist-info/LICENSE.md
pnwtools-2024.8.20.dist-info/METADATA
pnwtools-2024.8.20.dist-info/WHEEL
pnwtools-2024.8.20.dist-info/entry_points.txt
pnwtools-2024.8.20.dist-info/top_level.txt
pnwtools-2024.8.20.dist-info/RECORD
