Metadata-Version: 2.1
Name: pnwtools
Version: 2024.8.20
Summary: Tools for working with bioacoustics data
Author-email: Zack Ruff <zjruff@gmail.com>
Maintainer-email: Zack Ruff <zjruff@gmail.com>
License: GNU GENERAL PUBLIC LICENSE
Project-URL: Documentation, https://readthedocs.org
Project-URL: Repository, https://github.com/zjruff/pnwtools
Project-URL: Issues, https://github.com/zjruff/pnwtools/issues
Keywords: bioacoustics
Classifier: Development Status :: 4 - Beta
Classifier: Intended Audience :: Science/Research
Classifier: Programming Language :: Python :: 3
Classifier: License :: OSI Approved :: GNU General Public License v3 (GPLv3)
Classifier: Operating System :: OS Independent
Requires-Python: >=3.8
License-File: LICENSE.md
Requires-Dist: guano
